{
  "version": 1,
  "serviceConfiguration": {
    "apiName": "sampleapp",
    "serviceName": "AppSync",
    "gqlSchemaPath": "/Users/merlyn/Projects/Evergreen/Git/flutter_mqtt_riverpod/amplify/backend/api/sampleapp/schema.graphql",
    "defaultAuthType": {
      "mode": "API_KEY",
      "expirationTime": 30,
      "apiKeyExpirationDate": "2022-03-24T00:33:23.979Z",
      "keyDescription": "the API key"
    },
    "additionalAuthTypes": [
      {
        "mode": "AWS_IAM"
      },
      {
        "mode": "AMAZON_COGNITO_USER_POOLS",
        "cognitoUserPoolId": "authsampleapp"
      }
    ],
    "conflictResolution": {
      "defaultResolutionStrategy": {
        "type": "AUTOMERGE"
      }
    }
  }
}